{
  "id": "MAP_CAVE_OF_UNKNOWN",
  "name": "CaveOfUnknown",
  "layout": "LAYOUT_CAVE_OF_UNKNOWN",
  "music": "MUS_ABANDONED_SHIP",
  "region_map_section": "MAPSEC_GRANITE_CAVE",
  "requires_flash": false,
  "weather": "WEATHER_NONE",
  "map_type": "MAP_TYPE_UNDERGROUND",
  "allow_cycling": true,
  "allow_escaping": true,
  "allow_running": true,
  "show_map_name": true,
  "battle_scene": "MAP_BATTLE_SCENE_NORMAL",
  "connections": 0,
  "object_events": [

  ],
  "warp_events": [

  ],
  "coord_events": [
    {
      "type": "trigger",
      "x": 2,
      "y": 34,
      "elevation": 0,
      "var": "VAR_UNKNOWNCAVE",
      "var_value": "0",
      "script": "CaveofUnknown_EventScript"
    },
    {
      "type": "trigger",
      "x": 4,
      "y": 14,
      "elevation": 0,
      "var": "VAR_NAME_CALLED_TWICE",
      "var_value": "0",
      "script": "CaveofUnknown_EventScript_HearingThingsAgain"
    },
    {
      "type": "trigger",
      "x": 3,
      "y": 14,
      "elevation": 0,
      "var": "VAR_NAME_CALLED_TWICE",
      "var_value": "0",
      "script": "CaveofUnknown_EventScript_HearingThingsAgain"
    },
    {
      "type": "trigger",
      "x": 2,
      "y": 14,
      "elevation": 0,
      "var": "VAR_NAME_CALLED_TWICE",
      "var_value": "0",
      "script": "CaveofUnknown_EventScript_HearingThingsAgain"
    },
    {
      "type": "trigger",
      "x": 4,
      "y": 2,
      "elevation": 0,
      "var": "VAR_AWOKEN_FROM_DREAM",
      "var_value": "0",
      "script": "CaveofUnknown_EventScript_HeadedHome"
    },
    {
      "type": "trigger",
      "x": 3,
      "y": 2,
      "elevation": 0,
      "var": "VAR_AWOKEN_FROM_DREAM",
      "var_value": "0",
      "script": "CaveofUnknown_EventScript_HeadedHome"
    },
    {
      "type": "trigger",
      "x": 2,
      "y": 2,
      "elevation": 0,
      "var": "VAR_AWOKEN_FROM_DREAM",
      "var_value": "0",
      "script": "CaveofUnknown_EventScript_HeadedHome"
    },
    {
      "type": "trigger",
      "x": 4,
      "y": 28,
      "elevation": 0,
      "var": "VAR_NAME_CALLED_ONCE",
      "var_value": "0",
      "script": "CaveofUnknown_EventScript_HearingThings"
    },
    {
      "type": "trigger",
      "x": 3,
      "y": 28,
      "elevation": 0,
      "var": "VAR_NAME_CALLED_ONCE",
      "var_value": "0",
      "script": "CaveofUnknown_EventScript_HearingThings"
    },
    {
      "type": "trigger",
      "x": 2,
      "y": 28,
      "elevation": 0,
      "var": "VAR_NAME_CALLED_ONCE",
      "var_value": "0",
      "script": "CaveofUnknown_EventScript_HearingThings"
    },
    {
      "type": "trigger",
      "x": 4,
      "y": 34,
      "elevation": 0,
      "var": "VAR_UNKNOWNCAVE",
      "var_value": "0",
      "script": "CaveofUnknown_EventScript"
    },
    {
      "type": "trigger",
      "x": 3,
      "y": 34,
      "elevation": 0,
      "var": "VAR_UNKNOWNCAVE",
      "var_value": "0",
      "script": "CaveofUnknown_EventScript"
    }
  ],
  "bg_events": [

  ]
}
